main.py
sumup-0.1.0.dist-info/licenses/LICENSE
sumup-0.1.0.dist-info/METADATA
sumup-0.1.0.dist-info/WHEEL
sumup-0.1.0.dist-info/top_level.txt
sumup-0.1.0.dist-info/RECORD
