Metadata-Version: 2.4
Name: sumup
Version: 0.1.0
Summary: Add your description here
Requires-Python: >=3.13
License-File: LICENSE
Requires-Dist: ruff>=0.11.5
Dynamic: license-file
